{
    "$schema": "http://json-schema.org/schema#",
    "type": "object",
    "properties": {
        "context": {
            "type": "object",
            "properties": {
                "app": {
                    "type": "string"
                },
                "cluster": {
                    "type": "string"
                },
                "component": {
                    "type": "string"
                },
                "environment": {
                    "type": "string"
                },
                "scope": {
                    "type": "string"
                }
            }
        },
        "operator": {
            "type": "object",
            "properties": {
                "context": {
                    "type": "object",
                    "properties": {
                        "app": {
                            "type": "string"
                        },
                        "cluster": {
                            "type": "string"
                        },
                        "component": {
                            "type": "string"
                        },
                        "environment": {
                            "type": "string"
                        },
                        "scope": {
                            "type": "string"
                        }
                    }
                },
                "enabled": {
                    "type": "boolean"
                },
                "operatorGroup": {
                    "type": "object",
                    "properties": {
                        "enabled": {
                            "type": "boolean"
                        },
                        "hooked": {
                            "type": "boolean"
                        },
                        "name": {
                            "type": "string"
                        },
                        "namespace": {
                            "type": "string"
                        },
                        "providedAPIs": {
                            "type": "string"
                        }
                    }
                },
                "subscription": {
                    "type": "object",
                    "properties": {
                        "enabled": {
                            "type": "boolean"
                        },
                        "hooked": {
                            "type": "boolean"
                        },
                        "name": {
                            "type": "string"
                        },
                        "namespace": {
                            "type": "string"
                        },
                        "operator": {
                            "type": "object",
                            "properties": {
                                "channel": {
                                    "type": "string"
                                },
                                "csv": {
                                    "type": "string"
                                },
                                "name": {
                                    "type": "string"
                                },
                                "source": {
                                    "type": "object",
                                    "properties": {
                                        "name": {
                                            "type": "string"
                                        },
                                        "namespace": {
                                            "type": "string"
                                        }
                                    }
                                }
                            }
                        },
                        "version": {
                            "type": "string"
                        }
                    }
                }
            }
        },
        "operatorsec": {
            "type": "object",
            "properties": {
                "context": {
                    "type": "object",
                    "properties": {
                        "app": {
                            "type": "string"
                        },
                        "cluster": {
                            "type": "string"
                        },
                        "component": {
                            "type": "string"
                        },
                        "environment": {
                            "type": "string"
                        },
                        "scope": {
                            "type": "string"
                        }
                    }
                },
                "enabled": {
                    "type": "boolean"
                },
                "operatorGroup": {
                    "type": "object",
                    "properties": {
                        "enabled": {
                            "type": "boolean"
                        }
                    }
                },
                "subscription": {
                    "type": "object",
                    "properties": {
                        "enabled": {
                            "type": "boolean"
                        },
                        "hooked": {
                            "type": "boolean"
                        },
                        "name": {
                            "type": "string"
                        },
                        "namespace": {
                            "type": "string"
                        },
                        "operator": {
                            "type": "object",
                            "properties": {
                                "channel": {
                                    "type": "string"
                                },
                                "csv": {
                                    "type": "string"
                                },
                                "name": {
                                    "type": "string"
                                },
                                "source": {
                                    "type": "object",
                                    "properties": {
                                        "name": {
                                            "type": "string"
                                        },
                                        "namespace": {
                                            "type": "string"
                                        }
                                    }
                                }
                            }
                        },
                        "version": {
                            "type": "string"
                        }
                    }
                }
            }
        },
        "project": {
            "type": "object",
            "properties": {
                "context": {
                    "type": "object",
                    "properties": {
                        "app": {
                            "type": "string"
                        },
                        "cluster": {
                            "type": "string"
                        },
                        "component": {
                            "type": "string"
                        },
                        "environment": {
                            "type": "string"
                        },
                        "scope": {
                            "type": "string"
                        }
                    }
                },
                "enabled": {
                    "type": "boolean"
                },
                "project": {
                    "type": "object",
                    "properties": {
                        "description": {
                            "type": "string"
                        },
                        "display_name": {
                            "type": "string"
                        },
                        "enabled": {
                            "type": "boolean"
                        },
                        "hooked": {
                            "type": "boolean"
                        },
                        "name": {
                            "type": "string"
                        },
                        "type": {
                            "type": "string"
                        }
                    }
                }
            }
        },
        "quay": {
            "type": "object",
            "properties": {
                "admin": {
                    "type": "object",
                    "properties": {
                        "email": {
                            "type": "string"
                        },
                        "password": {
                            "type": "string"
                        },
                        "username": {
                            "type": "string"
                        }
                    }
                },
                "clair": {
                    "type": "object",
                    "properties": {
                        "enabled": {
                            "type": "boolean"
                        },
                        "image": {
                            "type": "string"
                        },
                        "size": {
                            "type": "string"
                        }
                    }
                },
                "db": {
                    "type": "object",
                    "properties": {
                        "creds": {
                            "type": "object",
                            "properties": {
                                "password": {
                                    "type": "string"
                                },
                                "root-password": {
                                    "type": "string"
                                },
                                "username": {
                                    "type": "string"
                                }
                            }
                        },
                        "image": {
                            "type": "string"
                        },
                        "name": {
                            "type": "string"
                        },
                        "size": {
                            "type": "string"
                        }
                    }
                },
                "enabled": {
                    "type": "boolean"
                },
                "hooked": {
                    "type": "boolean"
                },
                "image": {
                    "type": "string"
                },
                "pullSecretEnabled": {
                    "type": "boolean"
                },
                "redis": {
                    "type": "object",
                    "properties": {
                        "creds": {
                            "type": "object",
                            "properties": {
                                "password": {
                                    "type": "string"
                                }
                            }
                        },
                        "image": {
                            "type": "string"
                        }
                    }
                },
                "size": {
                    "type": "string"
                },
                "storageAccess": {
                    "type": "string"
                },
                "storageClass": {
                    "type": "string"
                }
            }
        },
        "rhn": {
            "type": "object",
            "properties": {
                "enabled": {
                    "type": "boolean"
                },
                "pwd": {
                    "type": "string"
                },
                "user": {
                    "type": "string"
                }
            }
        },
        "route": {
            "type": "object",
            "properties": {
                "enabled": {
                    "type": "boolean"
                },
                "name": {
                    "type": "string"
                }
            }
        }
    }
}
